dash_notice
