Metadata-Version: 2.1
Name: dash-notice
Version: 1.1.0
Summary: Dash Notice Component
Author: s_matsumoto <s_matsumoto@thinkup-sol.co.jp>
License: MIT
Classifier: Framework :: Dash
License-File: LICENSE
